Metadata-Version: 1.0
Name: Flask-CouchDBKit
Version: 0.3.5
Summary: Flask extension that provides integration with CouchDBKit.
Home-page: http://code.grid.in.th/
Author: Kridsada Thanabulpong
Author-email: sirn@ogsite.net
License: BSD
Platform: any
Classifier: Development Status :: 4 - Beta
Classifier: Environment :: Web Environment
Classifier: Intended Audience :: Developers
Classifier: License :: OSI Approved :: BSD License
Classifier: Operating System :: OS Independent
Classifier: Programming Language :: Python
Classifier: Topic :: Internet :: WWW/HTTP :: Dynamic Content
Classifier: Topic :: Software Development :: Libraries :: Python Modules
